{
  "data": [
    {
      "name": "BIRKDALE",
      "customersAffected": 201,
      "outagesCount": 2
    },
    {
      "name": "CHANDLER",
      "customersAffected": 4,
      "outagesCount": 1
    },
    {
      "name": "KALLANGUR",
      "customersAffected": 285,
      "outagesCount": 1
    },
    {
      "name": "NAMBOUR",
      "customersAffected": 41,
      "outagesCount": 1
    },
    {
      "name": "ONE MILE",
      "customersAffected": 6,
      "outagesCount": 1
    },
    {
      "name": "THORNESIDE",
      "customersAffected": 2,
      "outagesCount": 1
    }
  ]
}