{
  "data": [
    {
      "name": "CABOOLTURE",
      "customersAffected": 8,
      "outagesCount": 1
    },
    {
      "name": "CANUNGRA",
      "customersAffected": 28,
      "outagesCount": 1
    },
    {
      "name": "CHEVALLUM",
      "customersAffected": 10,
      "outagesCount": 1
    },
    {
      "name": "CURRUMBIN",
      "customersAffected": 97,
      "outagesCount": 1
    },
    {
      "name": "ELIMBAH",
      "customersAffected": 272,
      "outagesCount": 1
    },
    {
      "name": "FIG TREE POCKET",
      "customersAffected": 292,
      "outagesCount": 1
    },
    {
      "name": "GLENVIEW",
      "customersAffected": 22,
      "outagesCount": 1
    },
    {
      "name": "HEMMANT",
      "customersAffected": 4,
      "outagesCount": 1
    },
    {
      "name": "ILKLEY",
      "customersAffected": 135,
      "outagesCount": 1
    },
    {
      "name": "INDOOROOPILLY",
      "customersAffected": 95,
      "outagesCount": 2
    },
    {
      "name": "KANGAROO POINT",
      "customersAffected": 90,
      "outagesCount": 1
    },
    {
      "name": "KENMORE",
      "customersAffected": 312,
      "outagesCount": 3
    },
    {
      "name": "MERRIMAC",
      "customersAffected": 2,
      "outagesCount": 1
    },
    {
      "name": "MOOLOOLAH VALLEY",
      "customersAffected": 194,
      "outagesCount": 2
    },
    {
      "name": "NEWPORT",
      "customersAffected": 3,
      "outagesCount": 1
    },
    {
      "name": "PULLENVALE",
      "customersAffected": 57,
      "outagesCount": 3
    },
    {
      "name": "ROTHWELL",
      "customersAffected": 2,
      "outagesCount": 1
    },
    {
      "name": "SCARBOROUGH",
      "customersAffected": 51,
      "outagesCount": 1
    },
    {
      "name": "TANAWHA",
      "customersAffected": 5,
      "outagesCount": 1
    },
    {
      "name": "THE GAP",
      "customersAffected": 34,
      "outagesCount": 1
    },
    {
      "name": "VIRGINIA",
      "customersAffected": 60,
      "outagesCount": 1
    }
  ]
}