{
  "data": [
    {
      "name": "ARANA HILLS",
      "customersAffected": 51,
      "outagesCount": 1
    },
    {
      "name": "BUDERIM",
      "customersAffected": 3,
      "outagesCount": 1
    },
    {
      "name": "CARRARA",
      "customersAffected": 1058,
      "outagesCount": 1
    },
    {
      "name": "EASTERN HEIGHTS",
      "customersAffected": 105,
      "outagesCount": 1
    },
    {
      "name": "FLINDERS VIEW",
      "customersAffected": 7,
      "outagesCount": 1
    },
    {
      "name": "IPSWICH",
      "customersAffected": 109,
      "outagesCount": 1
    },
    {
      "name": "RACEVIEW",
      "customersAffected": 1897,
      "outagesCount": 1
    }
  ]
}