{
  "data": [
    {
      "name": "BALLARD",
      "customersAffected": 60,
      "outagesCount": 1
    },
    {
      "name": "BLUE MOUNTAIN HTS",
      "customersAffected": 15,
      "outagesCount": 1
    },
    {
      "name": "BRACKEN RIDGE",
      "customersAffected": 677,
      "outagesCount": 1
    },
    {
      "name": "CHUWAR",
      "customersAffected": 63,
      "outagesCount": 1
    },
    {
      "name": "FITZGIBBON",
      "customersAffected": 712,
      "outagesCount": 1
    },
    {
      "name": "MURPHYS CREEK",
      "customersAffected": 24,
      "outagesCount": 1
    }
  ]
}