{
  "data": [
    {
      "name": "ANDERLEIGH",
      "customersAffected": 1,
      "outagesCount": 1
    },
    {
      "name": "ARALUEN",
      "customersAffected": 73,
      "outagesCount": 1
    },
    {
      "name": "CHATSWORTH",
      "customersAffected": 302,
      "outagesCount": 1
    },
    {
      "name": "CORELLA",
      "customersAffected": 19,
      "outagesCount": 1
    },
    {
      "name": "GYMPIE",
      "customersAffected": 31,
      "outagesCount": 1
    },
    {
      "name": "NORTH DEEP CREEK",
      "customersAffected": 97,
      "outagesCount": 1
    },
    {
      "name": "NORTH MACLEAN",
      "customersAffected": 6,
      "outagesCount": 1
    },
    {
      "name": "SOUTH BRISBANE",
      "customersAffected": 1,
      "outagesCount": 1
    },
    {
      "name": "TAMAREE",
      "customersAffected": 349,
      "outagesCount": 1
    }
  ]
}