{
  "data": [
    {
      "name": "ALBION",
      "customersAffected": 24,
      "outagesCount": 1
    },
    {
      "name": "BLACKSOIL",
      "customersAffected": 10,
      "outagesCount": 1
    },
    {
      "name": "HAIGSLEA",
      "customersAffected": 29,
      "outagesCount": 1
    },
    {
      "name": "IRONBARK",
      "customersAffected": 67,
      "outagesCount": 1
    },
    {
      "name": "NOOSA HEADS",
      "customersAffected": 2,
      "outagesCount": 1
    },
    {
      "name": "PINE MOUNTAIN",
      "customersAffected": 138,
      "outagesCount": 1
    },
    {
      "name": "ROTHWELL",
      "customersAffected": 2,
      "outagesCount": 1
    }
  ]
}