{
  "data": [
    {
      "name": "BRIDGES",
      "customersAffected": 54,
      "outagesCount": 1
    },
    {
      "name": "COOLOOLABIN",
      "customersAffected": 65,
      "outagesCount": 1
    },
    {
      "name": "IMAGE FLAT",
      "customersAffected": 42,
      "outagesCount": 1
    },
    {
      "name": "KIAMBA",
      "customersAffected": 29,
      "outagesCount": 2
    },
    {
      "name": "KULANGOOR",
      "customersAffected": 154,
      "outagesCount": 1
    },
    {
      "name": "MACLEAY ISLAND",
      "customersAffected": 24,
      "outagesCount": 1
    },
    {
      "name": "NAMBOUR",
      "customersAffected": 181,
      "outagesCount": 1
    },
    {
      "name": "PINBARREN",
      "customersAffected": 5,
      "outagesCount": 1
    },
    {
      "name": "YANDINA",
      "customersAffected": 1330,
      "outagesCount": 2
    }
  ]
}