{
  "data": [
    {
      "name": "ACACIA RIDGE",
      "customersAffected": 403,
      "outagesCount": 1
    },
    {
      "name": "ALDERLEY",
      "customersAffected": 64,
      "outagesCount": 1
    },
    {
      "name": "AMAMOOR",
      "customersAffected": 11,
      "outagesCount": 1
    },
    {
      "name": "AMBERLEY",
      "customersAffected": 13,
      "outagesCount": 1
    },
    {
      "name": "AMITY",
      "customersAffected": 424,
      "outagesCount": 1
    },
    {
      "name": "ANNERLEY",
      "customersAffected": 924,
      "outagesCount": 4
    },
    {
      "name": "ANSTEAD",
      "customersAffected": 322,
      "outagesCount": 1
    },
    {
      "name": "ARCHERFIELD",
      "customersAffected": 21,
      "outagesCount": 1
    },
    {
      "name": "ASHGROVE",
      "customersAffected": 2382,
      "outagesCount": 7
    },
    {
      "name": "AUCHENFLOWER",
      "customersAffected": 187,
      "outagesCount": 1
    },
    {
      "name": "BARDON",
      "customersAffected": 2914,
      "outagesCount": 7
    },
    {
      "name": "BARELLAN POINT",
      "customersAffected": 395,
      "outagesCount": 1
    },
    {
      "name": "BELLBOWRIE",
      "customersAffected": 28,
      "outagesCount": 2
    },
    {
      "name": "BLACK MOUNTAIN",
      "customersAffected": 13,
      "outagesCount": 2
    },
    {
      "name": "BLACKSOIL",
      "customersAffected": 54,
      "outagesCount": 1
    },
    {
      "name": "BLI BLI",
      "customersAffected": 963,
      "outagesCount": 1
    },
    {
      "name": "BOOVAL",
      "customersAffected": 63,
      "outagesCount": 2
    },
    {
      "name": "BOREEN POINT",
      "customersAffected": 60,
      "outagesCount": 1
    },
    {
      "name": "BOWEN HILLS",
      "customersAffected": 43,
      "outagesCount": 1
    },
    {
      "name": "BRASSALL",
      "customersAffected": 2,
      "outagesCount": 1
    },
    {
      "name": "BRIDGES",
      "customersAffected": 60,
      "outagesCount": 2
    },
    {
      "name": "BROOKFIELD",
      "customersAffected": 1259,
      "outagesCount": 4
    },
    {
      "name": "BUNDAMBA",
      "customersAffected": 260,
      "outagesCount": 1
    },
    {
      "name": "CEDAR POCKET",
      "customersAffected": 12,
      "outagesCount": 1
    },
    {
      "name": "CHAPEL HILL",
      "customersAffected": 3367,
      "outagesCount": 3
    },
    {
      "name": "CHELMER",
      "customersAffected": 1171,
      "outagesCount": 2
    },
    {
      "name": "CHURCHABLE",
      "customersAffected": 31,
      "outagesCount": 2
    },
    {
      "name": "CHURCHILL",
      "customersAffected": 36,
      "outagesCount": 1
    },
    {
      "name": "CHUWAR",
      "customersAffected": 764,
      "outagesCount": 1
    },
    {
      "name": "CLONTARF",
      "customersAffected": 28,
      "outagesCount": 1
    },
    {
      "name": "COLEYVILLE",
      "customersAffected": 3,
      "outagesCount": 1
    },
    {
      "name": "COMO",
      "customersAffected": 25,
      "outagesCount": 1
    },
    {
      "name": "COOLABINE",
      "customersAffected": 4,
      "outagesCount": 1
    },
    {
      "name": "COOLOOLA",
      "customersAffected": 1,
      "outagesCount": 1
    },
    {
      "name": "COOLOOLABIN",
      "customersAffected": 65,
      "outagesCount": 1
    },
    {
      "name": "COORAN",
      "customersAffected": 168,
      "outagesCount": 3
    },
    {
      "name": "COOTHARABA",
      "customersAffected": 28,
      "outagesCount": 2
    },
    {
      "name": "CORINDA",
      "customersAffected": 1224,
      "outagesCount": 4
    },
    {
      "name": "CORNUBIA",
      "customersAffected": 889,
      "outagesCount": 1
    },
    {
      "name": "CRESTMEAD",
      "customersAffected": 75,
      "outagesCount": 1
    },
    {
      "name": "DAGUN",
      "customersAffected": 4,
      "outagesCount": 1
    },
    {
      "name": "DARRA",
      "customersAffected": 1538,
      "outagesCount": 4
    },
    {
      "name": "DAYBORO",
      "customersAffected": 7,
      "outagesCount": 1
    },
    {
      "name": "DEEBING HEIGHTS",
      "customersAffected": 586,
      "outagesCount": 1
    },
    {
      "name": "DINMORE",
      "customersAffected": 54,
      "outagesCount": 2
    },
    {
      "name": "DUNWICH",
      "customersAffected": 42,
      "outagesCount": 1
    },
    {
      "name": "EAGLE FARM",
      "customersAffected": 32,
      "outagesCount": 1
    },
    {
      "name": "EASTERN HEIGHTS",
      "customersAffected": 2,
      "outagesCount": 1
    },
    {
      "name": "EBBW VALE",
      "customersAffected": 25,
      "outagesCount": 1
    },
    {
      "name": "EBENEZER",
      "customersAffected": 1,
      "outagesCount": 1
    },
    {
      "name": "FEDERAL",
      "customersAffected": 6,
      "outagesCount": 1
    },
    {
      "name": "FIG TREE POCKET",
      "customersAffected": 1561,
      "outagesCount": 5
    },
    {
      "name": "FLINDERS VIEW",
      "customersAffected": 574,
      "outagesCount": 1
    },
    {
      "name": "GHEERULLA",
      "customersAffected": 62,
      "outagesCount": 1
    },
    {
      "name": "GILLDORA",
      "customersAffected": 20,
      "outagesCount": 1
    },
    {
      "name": "GRACEVILLE",
      "customersAffected": 1837,
      "outagesCount": 3
    },
    {
      "name": "GRANGE",
      "customersAffected": 15,
      "outagesCount": 1
    },
    {
      "name": "GRANTHAM",
      "customersAffected": 52,
      "outagesCount": 1
    },
    {
      "name": "GREENBANK",
      "customersAffected": 2,
      "outagesCount": 1
    },
    {
      "name": "GREENSLOPES",
      "customersAffected": 1141,
      "outagesCount": 2
    },
    {
      "name": "HAIGSLEA",
      "customersAffected": 34,
      "outagesCount": 1
    },
    {
      "name": "HEMMANT",
      "customersAffected": 4,
      "outagesCount": 1
    },
    {
      "name": "IMAGE FLAT",
      "customersAffected": 42,
      "outagesCount": 1
    },
    {
      "name": "INALA",
      "customersAffected": 1215,
      "outagesCount": 2
    },
    {
      "name": "INDOOROOPILLY",
      "customersAffected": 3239,
      "outagesCount": 10
    },
    {
      "name": "IPSWICH",
      "customersAffected": 310,
      "outagesCount": 2
    },
    {
      "name": "IRONBARK",
      "customersAffected": 84,
      "outagesCount": 1
    },
    {
      "name": "JINDALEE",
      "customersAffected": 1018,
      "outagesCount": 4
    },
    {
      "name": "KARALEE",
      "customersAffected": 789,
      "outagesCount": 2
    },
    {
      "name": "KARRABIN",
      "customersAffected": 31,
      "outagesCount": 1
    },
    {
      "name": "KENILWORTH",
      "customersAffected": 48,
      "outagesCount": 1
    },
    {
      "name": "KENMORE",
      "customersAffected": 3703,
      "outagesCount": 6
    },
    {
      "name": "KENMORE HILLS",
      "customersAffected": 904,
      "outagesCount": 3
    },
    {
      "name": "KIA ORA",
      "customersAffected": 11,
      "outagesCount": 1
    },
    {
      "name": "KIAMBA",
      "customersAffected": 29,
      "outagesCount": 2
    },
    {
      "name": "KIN KIN",
      "customersAffected": 416,
      "outagesCount": 1
    },
    {
      "name": "KULANGOOR",
      "customersAffected": 154,
      "outagesCount": 1
    },
    {
      "name": "KYBONG",
      "customersAffected": 8,
      "outagesCount": 1
    },
    {
      "name": "LACEYS CREEK",
      "customersAffected": 75,
      "outagesCount": 1
    },
    {
      "name": "LAGOON POCKET",
      "customersAffected": 50,
      "outagesCount": 1
    },
    {
      "name": "LOCKYER",
      "customersAffected": 3,
      "outagesCount": 1
    },
    {
      "name": "LOCKYER WATERS",
      "customersAffected": 165,
      "outagesCount": 1
    },
    {
      "name": "LOWER MOUNT WALKER",
      "customersAffected": 34,
      "outagesCount": 2
    },
    {
      "name": "MAROOCHY RIVER",
      "customersAffected": 617,
      "outagesCount": 1
    },
    {
      "name": "MERRYVALE",
      "customersAffected": 1,
      "outagesCount": 1
    },
    {
      "name": "MOGGILL",
      "customersAffected": 8,
      "outagesCount": 1
    },
    {
      "name": "MOORANG",
      "customersAffected": 31,
      "outagesCount": 1
    },
    {
      "name": "MOTHAR MOUNTAIN",
      "customersAffected": 66,
      "outagesCount": 1
    },
    {
      "name": "MOUNT FORBES",
      "customersAffected": 1,
      "outagesCount": 1
    },
    {
      "name": "MOUNT WALKER",
      "customersAffected": 59,
      "outagesCount": 1
    },
    {
      "name": "MOUNT WALKER WEST",
      "customersAffected": 1,
      "outagesCount": 1
    },
    {
      "name": "MOY POCKET",
      "customersAffected": 1,
      "outagesCount": 1
    },
    {
      "name": "MT COOTTHA",
      "customersAffected": 11,
      "outagesCount": 2
    },
    {
      "name": "MURPHYS CREEK",
      "customersAffected": 9,
      "outagesCount": 1
    },
    {
      "name": "MUTDAPILLY",
      "customersAffected": 28,
      "outagesCount": 1
    },
    {
      "name": "NAMBOUR",
      "customersAffected": 181,
      "outagesCount": 1
    },
    {
      "name": "NEERDIE",
      "customersAffected": 55,
      "outagesCount": 1
    },
    {
      "name": "NEW CHUM",
      "customersAffected": 8,
      "outagesCount": 1
    },
    {
      "name": "NINDERRY",
      "customersAffected": 354,
      "outagesCount": 1
    },
    {
      "name": "NORTH ARM",
      "customersAffected": 2,
      "outagesCount": 1
    },
    {
      "name": "NORTH BOOVAL",
      "customersAffected": 482,
      "outagesCount": 1
    },
    {
      "name": "NTH STRADBROKE ISLD",
      "customersAffected": 36,
      "outagesCount": 1
    },
    {
      "name": "OXLEY",
      "customersAffected": 769,
      "outagesCount": 6
    },
    {
      "name": "PADDINGTON",
      "customersAffected": 760,
      "outagesCount": 1
    },
    {
      "name": "PEAK CROSSING",
      "customersAffected": 48,
      "outagesCount": 2
    },
    {
      "name": "PINBARREN",
      "customersAffected": 132,
      "outagesCount": 1
    },
    {
      "name": "PINE MOUNTAIN",
      "customersAffected": 338,
      "outagesCount": 1
    },
    {
      "name": "PINJARRA HILLS",
      "customersAffected": 78,
      "outagesCount": 4
    },
    {
      "name": "PINKENBA",
      "customersAffected": 8,
      "outagesCount": 1
    },
    {
      "name": "POMONA",
      "customersAffected": 1,
      "outagesCount": 1
    },
    {
      "name": "POSTMANS RIDGE",
      "customersAffected": 9,
      "outagesCount": 1
    },
    {
      "name": "PULLENVALE",
      "customersAffected": 913,
      "outagesCount": 4
    },
    {
      "name": "PURGA",
      "customersAffected": 52,
      "outagesCount": 2
    },
    {
      "name": "RACEVIEW",
      "customersAffected": 1118,
      "outagesCount": 1
    },
    {
      "name": "RAINBOW BEACH",
      "customersAffected": 1,
      "outagesCount": 1
    },
    {
      "name": "RED HILL",
      "customersAffected": 105,
      "outagesCount": 1
    },
    {
      "name": "REDWOOD",
      "customersAffected": 3,
      "outagesCount": 1
    },
    {
      "name": "RICHLANDS",
      "customersAffected": 349,
      "outagesCount": 2
    },
    {
      "name": "RINGTAIL CREEK",
      "customersAffected": 5,
      "outagesCount": 1
    },
    {
      "name": "RIPLEY",
      "customersAffected": 1306,
      "outagesCount": 2
    },
    {
      "name": "ROPELEY",
      "customersAffected": 1,
      "outagesCount": 1
    },
    {
      "name": "ROSEVALE",
      "customersAffected": 135,
      "outagesCount": 1
    },
    {
      "name": "SEVENTEEN MILE ROCKS",
      "customersAffected": 292,
      "outagesCount": 2
    },
    {
      "name": "SHERWOOD",
      "customersAffected": 1955,
      "outagesCount": 6
    },
    {
      "name": "SILKSTONE",
      "customersAffected": 626,
      "outagesCount": 2
    },
    {
      "name": "SINNAMON PARK",
      "customersAffected": 2,
      "outagesCount": 2
    },
    {
      "name": "SOUTH RIPLEY",
      "customersAffected": 2,
      "outagesCount": 1
    },
    {
      "name": "SPRING CREEK",
      "customersAffected": 87,
      "outagesCount": 2
    },
    {
      "name": "ST LUCIA",
      "customersAffected": 351,
      "outagesCount": 4
    },
    {
      "name": "STAFFORD",
      "customersAffected": 98,
      "outagesCount": 1
    },
    {
      "name": "STONES CORNER",
      "customersAffected": 11,
      "outagesCount": 1
    },
    {
      "name": "SUMNER",
      "customersAffected": 42,
      "outagesCount": 1
    },
    {
      "name": "TANDUR",
      "customersAffected": 17,
      "outagesCount": 1
    },
    {
      "name": "TARINGA",
      "customersAffected": 141,
      "outagesCount": 2
    },
    {
      "name": "TENNYSON",
      "customersAffected": 54,
      "outagesCount": 1
    },
    {
      "name": "THE GAP",
      "customersAffected": 355,
      "outagesCount": 1
    },
    {
      "name": "TOOWONG",
      "customersAffected": 408,
      "outagesCount": 2
    },
    {
      "name": "TRAVESTON",
      "customersAffected": 1,
      "outagesCount": 1
    },
    {
      "name": "UPPER BROOKFIELD",
      "customersAffected": 346,
      "outagesCount": 1
    },
    {
      "name": "VALDORA",
      "customersAffected": 39,
      "outagesCount": 1
    },
    {
      "name": "WACOL",
      "customersAffected": 3,
      "outagesCount": 1
    },
    {
      "name": "WALLOON",
      "customersAffected": 121,
      "outagesCount": 1
    },
    {
      "name": "WEST IPSWICH",
      "customersAffected": 49,
      "outagesCount": 1
    },
    {
      "name": "WILLOWBANK",
      "customersAffected": 418,
      "outagesCount": 1
    },
    {
      "name": "WITHCOTT",
      "customersAffected": 310,
      "outagesCount": 2
    },
    {
      "name": "WOOLLOONGABBA",
      "customersAffected": 439,
      "outagesCount": 1
    },
    {
      "name": "WYNNUM",
      "customersAffected": 142,
      "outagesCount": 1
    },
    {
      "name": "YANDINA",
      "customersAffected": 763,
      "outagesCount": 4
    },
    {
      "name": "YANDINA CREEK",
      "customersAffected": 1,
      "outagesCount": 1
    },
    {
      "name": "YEERONGPILLY",
      "customersAffected": 18,
      "outagesCount": 1
    }
  ]
}