{
  "data": [
    {
      "name": "ARMSTRONG CREEK",
      "customersAffected": 2,
      "outagesCount": 1
    },
    {
      "name": "ASHGROVE",
      "customersAffected": 1028,
      "outagesCount": 2
    },
    {
      "name": "ATKINSONS DAM",
      "customersAffected": 1,
      "outagesCount": 1
    },
    {
      "name": "BALD HILLS",
      "customersAffected": 58,
      "outagesCount": 2
    },
    {
      "name": "BALD KNOB",
      "customersAffected": 17,
      "outagesCount": 1
    },
    {
      "name": "BANKSIA BEACH",
      "customersAffected": 62,
      "outagesCount": 2
    },
    {
      "name": "BEACHMERE",
      "customersAffected": 459,
      "outagesCount": 3
    },
    {
      "name": "BELLARA",
      "customersAffected": 45,
      "outagesCount": 1
    },
    {
      "name": "BELLI PARK",
      "customersAffected": 13,
      "outagesCount": 2
    },
    {
      "name": "BELMONT",
      "customersAffected": 786,
      "outagesCount": 1
    },
    {
      "name": "BLENHEIM",
      "customersAffected": 1,
      "outagesCount": 1
    },
    {
      "name": "BLI BLI",
      "customersAffected": 79,
      "outagesCount": 1
    },
    {
      "name": "BOLLIER",
      "customersAffected": 8,
      "outagesCount": 1
    },
    {
      "name": "BONGAREE",
      "customersAffected": 139,
      "outagesCount": 2
    },
    {
      "name": "BOREEN POINT",
      "customersAffected": 296,
      "outagesCount": 1
    },
    {
      "name": "BRACALBA",
      "customersAffected": 2,
      "outagesCount": 1
    },
    {
      "name": "BROOLOO",
      "customersAffected": 26,
      "outagesCount": 1
    },
    {
      "name": "BUARABA",
      "customersAffected": 60,
      "outagesCount": 1
    },
    {
      "name": "BUDDINA",
      "customersAffected": 79,
      "outagesCount": 2
    },
    {
      "name": "BUDERIM",
      "customersAffected": 26,
      "outagesCount": 1
    },
    {
      "name": "BURPENGARY",
      "customersAffected": 94,
      "outagesCount": 3
    },
    {
      "name": "BURPENGARY EAST",
      "customersAffected": 12,
      "outagesCount": 1
    },
    {
      "name": "CABOOLTURE",
      "customersAffected": 249,
      "outagesCount": 5
    },
    {
      "name": "CALVERT",
      "customersAffected": 2,
      "outagesCount": 1
    },
    {
      "name": "CAMBROON",
      "customersAffected": 1,
      "outagesCount": 1
    },
    {
      "name": "CARINA",
      "customersAffected": 2,
      "outagesCount": 1
    },
    {
      "name": "CARINDALE",
      "customersAffected": 141,
      "outagesCount": 1
    },
    {
      "name": "CARTERS RIDGE",
      "customersAffected": 34,
      "outagesCount": 2
    },
    {
      "name": "CASHMERE",
      "customersAffected": 4,
      "outagesCount": 1
    },
    {
      "name": "CEDARTON",
      "customersAffected": 1,
      "outagesCount": 1
    },
    {
      "name": "CHEVALLUM",
      "customersAffected": 11,
      "outagesCount": 1
    },
    {
      "name": "CHURCHABLE",
      "customersAffected": 23,
      "outagesCount": 1
    },
    {
      "name": "CLARENDON",
      "customersAffected": 1,
      "outagesCount": 1
    },
    {
      "name": "CLOSEBURN",
      "customersAffected": 21,
      "outagesCount": 3
    },
    {
      "name": "COMO",
      "customersAffected": 30,
      "outagesCount": 2
    },
    {
      "name": "CONONDALE",
      "customersAffected": 11,
      "outagesCount": 2
    },
    {
      "name": "COOLUM BEACH",
      "customersAffected": 48,
      "outagesCount": 1
    },
    {
      "name": "COOMERA",
      "customersAffected": 1,
      "outagesCount": 1
    },
    {
      "name": "COOMINYA",
      "customersAffected": 1,
      "outagesCount": 1
    },
    {
      "name": "COONDOO",
      "customersAffected": 47,
      "outagesCount": 1
    },
    {
      "name": "COORAN",
      "customersAffected": 18,
      "outagesCount": 1
    },
    {
      "name": "COOROIBAH",
      "customersAffected": 9,
      "outagesCount": 1
    },
    {
      "name": "COOROY",
      "customersAffected": 2,
      "outagesCount": 1
    },
    {
      "name": "COOTHARABA",
      "customersAffected": 275,
      "outagesCount": 3
    },
    {
      "name": "D'AGUILAR",
      "customersAffected": 165,
      "outagesCount": 2
    },
    {
      "name": "DAKABIN",
      "customersAffected": 2,
      "outagesCount": 2
    },
    {
      "name": "DAYBORO",
      "customersAffected": 24,
      "outagesCount": 2
    },
    {
      "name": "DECEPTION BAY",
      "customersAffected": 104,
      "outagesCount": 3
    },
    {
      "name": "DELANEYS CREEK",
      "customersAffected": 19,
      "outagesCount": 1
    },
    {
      "name": "DONNYBROOK",
      "customersAffected": 411,
      "outagesCount": 2
    },
    {
      "name": "DOONAN",
      "customersAffected": 55,
      "outagesCount": 2
    },
    {
      "name": "EATONS HILL",
      "customersAffected": 87,
      "outagesCount": 1
    },
    {
      "name": "EDENS LANDING",
      "customersAffected": 41,
      "outagesCount": 1
    },
    {
      "name": "ELIMBAH",
      "customersAffected": 32,
      "outagesCount": 1
    },
    {
      "name": "EUDLO",
      "customersAffected": 4,
      "outagesCount": 1
    },
    {
      "name": "GATTON",
      "customersAffected": 4,
      "outagesCount": 1
    },
    {
      "name": "GLASSHOUSE MOUNTAINS",
      "customersAffected": 3,
      "outagesCount": 2
    },
    {
      "name": "GLENVIEW",
      "customersAffected": 5,
      "outagesCount": 1
    },
    {
      "name": "GODWIN BEACH",
      "customersAffected": 53,
      "outagesCount": 2
    },
    {
      "name": "GOOMBOORIAN",
      "customersAffected": 2,
      "outagesCount": 1
    },
    {
      "name": "GORDON PARK",
      "customersAffected": 237,
      "outagesCount": 1
    },
    {
      "name": "HAZELDEAN",
      "customersAffected": 146,
      "outagesCount": 1
    },
    {
      "name": "HOPE ISLAND",
      "customersAffected": 24,
      "outagesCount": 1
    },
    {
      "name": "IRONBARK",
      "customersAffected": 22,
      "outagesCount": 1
    },
    {
      "name": "JIMNA",
      "customersAffected": 66,
      "outagesCount": 1
    },
    {
      "name": "KALLANGUR",
      "customersAffected": 61,
      "outagesCount": 1
    },
    {
      "name": "KARRABIN",
      "customersAffected": 4,
      "outagesCount": 1
    },
    {
      "name": "KEDRON",
      "customersAffected": 163,
      "outagesCount": 1
    },
    {
      "name": "KENILWORTH",
      "customersAffected": 1,
      "outagesCount": 1
    },
    {
      "name": "KERRY",
      "customersAffected": 1,
      "outagesCount": 1
    },
    {
      "name": "KILCOY",
      "customersAffected": 2,
      "outagesCount": 1
    },
    {
      "name": "KIN KIN",
      "customersAffected": 133,
      "outagesCount": 1
    },
    {
      "name": "KINGAHAM",
      "customersAffected": 1,
      "outagesCount": 1
    },
    {
      "name": "KURWONGBAH",
      "customersAffected": 11,
      "outagesCount": 2
    },
    {
      "name": "LAKE MACDONALD",
      "customersAffected": 48,
      "outagesCount": 1
    },
    {
      "name": "LOWER MOUNT WALKER",
      "customersAffected": 1,
      "outagesCount": 1
    },
    {
      "name": "MALENY",
      "customersAffected": 28,
      "outagesCount": 1
    },
    {
      "name": "MANGO HILL",
      "customersAffected": 2,
      "outagesCount": 1
    },
    {
      "name": "MAROOCHY RIVER",
      "customersAffected": 17,
      "outagesCount": 1
    },
    {
      "name": "MELDALE",
      "customersAffected": 106,
      "outagesCount": 3
    },
    {
      "name": "MONTVILLE",
      "customersAffected": 6,
      "outagesCount": 2
    },
    {
      "name": "MOORINA",
      "customersAffected": 59,
      "outagesCount": 1
    },
    {
      "name": "MORAYFIELD",
      "customersAffected": 51,
      "outagesCount": 1
    },
    {
      "name": "MORNINGSIDE",
      "customersAffected": 1,
      "outagesCount": 1
    },
    {
      "name": "MOUNT COOLUM",
      "customersAffected": 133,
      "outagesCount": 2
    },
    {
      "name": "MOUNT SAMSON",
      "customersAffected": 2,
      "outagesCount": 1
    },
    {
      "name": "MT PLEASANT",
      "customersAffected": 105,
      "outagesCount": 3
    },
    {
      "name": "NARANGBA",
      "customersAffected": 58,
      "outagesCount": 2
    },
    {
      "name": "NINDERRY",
      "customersAffected": 8,
      "outagesCount": 1
    },
    {
      "name": "NINGI",
      "customersAffected": 491,
      "outagesCount": 5
    },
    {
      "name": "NORTH DEEP CREEK",
      "customersAffected": 3,
      "outagesCount": 2
    },
    {
      "name": "OCEAN VIEW",
      "customersAffected": 10,
      "outagesCount": 1
    },
    {
      "name": "PEREGIAN BEACH",
      "customersAffected": 173,
      "outagesCount": 2
    },
    {
      "name": "PETRIE",
      "customersAffected": 96,
      "outagesCount": 1
    },
    {
      "name": "PIMPAMA",
      "customersAffected": 1,
      "outagesCount": 1
    },
    {
      "name": "PINKENBA",
      "customersAffected": 4,
      "outagesCount": 2
    },
    {
      "name": "POMONA",
      "customersAffected": 23,
      "outagesCount": 4
    },
    {
      "name": "REDBANK PLAINS",
      "customersAffected": 1,
      "outagesCount": 1
    },
    {
      "name": "REESVILLE",
      "customersAffected": 10,
      "outagesCount": 1
    },
    {
      "name": "RIDGEWOOD",
      "customersAffected": 1,
      "outagesCount": 1
    },
    {
      "name": "RINGTAIL CREEK",
      "customersAffected": 6,
      "outagesCount": 1
    },
    {
      "name": "SAMSONVALE",
      "customersAffected": 6,
      "outagesCount": 1
    },
    {
      "name": "SANDY CREEK",
      "customersAffected": 19,
      "outagesCount": 1
    },
    {
      "name": "SHEEP STATION CREEK",
      "customersAffected": 25,
      "outagesCount": 1
    },
    {
      "name": "SOUTH RIPLEY",
      "customersAffected": 2008,
      "outagesCount": 1
    },
    {
      "name": "SPRING CREEK",
      "customersAffected": 82,
      "outagesCount": 1
    },
    {
      "name": "SPRING HILL",
      "customersAffected": 66,
      "outagesCount": 1
    },
    {
      "name": "STANMORE",
      "customersAffected": 67,
      "outagesCount": 1
    },
    {
      "name": "SWANBANK",
      "customersAffected": 1,
      "outagesCount": 1
    },
    {
      "name": "TAMAREE",
      "customersAffected": 20,
      "outagesCount": 1
    },
    {
      "name": "TINBEERWAH",
      "customersAffected": 43,
      "outagesCount": 1
    },
    {
      "name": "TINGALPA",
      "customersAffected": 386,
      "outagesCount": 1
    },
    {
      "name": "TOORBUL",
      "customersAffected": 55,
      "outagesCount": 2
    },
    {
      "name": "TUCHEKOI",
      "customersAffected": 2,
      "outagesCount": 1
    },
    {
      "name": "UPPER CABOOLTURE",
      "customersAffected": 5,
      "outagesCount": 1
    },
    {
      "name": "VETERAN",
      "customersAffected": 3,
      "outagesCount": 2
    },
    {
      "name": "WAMURAN",
      "customersAffected": 37,
      "outagesCount": 4
    },
    {
      "name": "WAMURAN BASIN",
      "customersAffected": 4,
      "outagesCount": 1
    },
    {
      "name": "WHITE ROCK",
      "customersAffected": 500,
      "outagesCount": 1
    },
    {
      "name": "WHITESIDE",
      "customersAffected": 57,
      "outagesCount": 1
    },
    {
      "name": "WOLVI",
      "customersAffected": 150,
      "outagesCount": 1
    },
    {
      "name": "WOODFORD",
      "customersAffected": 2,
      "outagesCount": 1
    }
  ]
}