[
  {
    "StatusHeading": "Known power outage - working to restore power",
    "Area": "Heathcote",
    "Cause": "Under investigation",
    "Customers": "119",
    "EstRestTime": "2026-01-09T00:00:00",
    "StartDateTime": "2026-01-08T18:05:00",
    "WebId": 178389,
    "Status": 1
  },
  {
    "StatusHeading": "Known power outage",
    "Area": "Neutral Bay",
    "Cause": "Under investigation",
    "Customers": "76",
    "EstRestTime": "2026-01-09T00:00:00",
    "StartDateTime": "2026-01-08T20:45:00",
    "WebId": 178410,
    "Status": 0
  },
  {
    "StatusHeading": "Known power outage - working to restore power",
    "Area": "Cooks Hill, Hamilton, Hamilton South, Merewether, Newcastle, Newcastle West, the Junction",
    "Cause": "Underground cable fault",
    "Customers": "133",
    "EstRestTime": "2026-01-09T10:00:00",
    "StartDateTime": "2026-01-08T19:20:00",
    "WebId": 178395,
    "Status": 1
  }
]