[
  {
    "StatusHeading": "Ongoing network repairs",
    "Area": "Lilyfield, Rozelle",
    "Cause": "Under investigation",
    "Customers": "less than 10",
    "EstRestTime": "2023-01-09T16:00:00",
    "StartDateTime": "2023-01-04T17:10:00",
    "WebId": 94023,
    "Status": 2
  },
  {
    "StatusHeading": "Removing hazards and diagnosing network fault",
    "Area": "Illawong",
    "Cause": "Underground cable fault",
    "Customers": "36",
    "EstRestTime": "2023-01-09T16:00:00",
    "StartDateTime": "2023-01-09T01:55:00",
    "WebId": 94112,
    "Status": 1
  },
  {
    "StatusHeading": "Ongoing network repairs",
    "Area": "Luskintyre, Lochinvar, Windermere",
    "Cause": "Under investigation",
    "Customers": "77",
    "EstRestTime": "2023-01-08T22:30:00",
    "StartDateTime": "2023-01-08T20:20:00",
    "WebId": 94107,
    "Status": 2
  }
]
