[
  {
    "StatusHeading": "Known power outage - working to restore power",
    "Area": "Valentine",
    "Cause": "Underground cable fault",
    "Customers": "21",
    "EstRestTime": "2023-11-25T06:30:00",
    "StartDateTime": "2023-11-24T21:35:00",
    "WebId": 98613,
    "Status": 2
  },
  {
    "StatusHeading": "Known power outage",
    "Area": "Waratah, Waratah West, Wallsend, Birmingham Gardens, Warabrook, Lambton, North Lambton, Mayfield West, Mayfield, Georgetown, Callaghan, Shortland",
    "Cause": "Under investigation",
    "Customers": "1581",
    "EstRestTime": "2023-11-26T23:00:00",
    "StartDateTime": "2023-11-26T20:45:00",
    "WebId": 98637,
    "Status": 0
  },
  {
    "StatusHeading": "Known power outage",
    "Area": "Birmingham Gardens",
    "Cause": "Under investigation",
    "Customers": "66",
    "EstRestTime": "2023-11-26T23:00:00",
    "StartDateTime": "2023-11-26T20:50:00",
    "WebId": 98638,
    "Status": 0
  }
]
