[
  {
    "StatusHeading": "Known power outage - working to restore power",
    "Area": "Vaucluse, Watsons Bay",
    "Cause": "Emergency repairs",
    "Customers": "55",
    "EstRestTime": "2023-08-04T04:00:00",
    "StartDateTime": "2023-08-04T01:55:00",
    "WebId": 97176,
    "Status": 1
  },
  {
    "StatusHeading": "Known power outage",
    "Area": "Elanora Heights",
    "Cause": "Under investigation",
    "Customers": "76",
    "EstRestTime": "2023-08-04T05:00:00",
    "StartDateTime": "2023-08-04T02:55:00",
    "WebId": 97177,
    "Status": 0
  }
]
