[
  {
    "StatusHeading": "Known power outage",
    "Area": "Bellevue Hill",
    "Cause": "Under investigation",
    "Customers": "24",
    "EstRestTime": "2024-04-28T18:00:00",
    "StartDateTime": "2024-04-28T15:55:00",
    "WebId": 101690,
    "Status": 0
  },
  {
    "StatusHeading": "Known power outage",
    "Area": "Rothbury, Pokolbin",
    "Cause": "Under investigation",
    "Customers": "less than 10",
    "EstRestTime": "2024-04-28T18:30:00",
    "StartDateTime": "2024-04-28T16:15:00",
    "WebId": 101691,
    "Status": 0
  }
]
