[
  {
    "StatusHeading": "Known power outage - working to restore power",
    "Area": "Singleton",
    "Cause": "Under investigation",
    "Customers": "less than 10",
    "EstRestTime": "2025-11-24T12:30:00",
    "StartDateTime": "2025-10-22T15:40:00",
    "WebId": 158557,
    "Status": 2
  },
  {
    "StatusHeading": "Known power outage - working to restore power",
    "Area": "Belmont",
    "Cause": "Under investigation",
    "Customers": "11",
    "EstRestTime": "2025-11-22T23:00:00",
    "StartDateTime": "2025-11-22T07:50:00",
    "WebId": 165502,
    "Status": 2
  },
  {
    "StatusHeading": "Known power outage - working to restore power",
    "Area": "Strathfield",
    "Cause": "Under investigation",
    "Customers": "11",
    "EstRestTime": "2025-11-24T06:00:00",
    "StartDateTime": "2025-11-23T10:45:00",
    "WebId": 165676,
    "Status": 2
  },
  {
    "StatusHeading": "Known power outage - working to restore power",
    "Area": "Sydney",
    "Cause": "Underground cable fault",
    "Customers": "25",
    "EstRestTime": "2025-11-25T18:00:00",
    "StartDateTime": "2025-11-24T23:55:00",
    "WebId": 165878,
    "Status": 2
  },
  {
    "StatusHeading": "Known power outage - working to restore power",
    "Area": "Mangrove Mountain",
    "Cause": "Under investigation",
    "Customers": "14",
    "EstRestTime": "2025-11-25T17:00:00",
    "StartDateTime": "2025-11-25T10:10:00",
    "WebId": 165957,
    "Status": 1
  },
  {
    "StatusHeading": "Known power outage - working to restore power",
    "Area": "Broke",
    "Cause": "Trees over power lines",
    "Customers": "16",
    "EstRestTime": "2025-11-25T18:00:00",
    "StartDateTime": "2025-11-25T11:15:00",
    "WebId": 165971,
    "Status": 1
  },
  {
    "StatusHeading": "Known power outage",
    "Area": "Berowra Heights",
    "Cause": "Under investigation",
    "Customers": "52",
    "EstRestTime": "2025-11-25T17:30:00",
    "StartDateTime": "2025-11-25T12:15:00",
    "WebId": 165985,
    "Status": 0
  }
]