[
  {
    "StatusHeading": "Removing hazards and diagnosing network fault",
    "Area": "Cooranbong",
    "Cause": "Under investigation",
    "Customers": "40",
    "EstRestTime": "2022-06-15T18:30:00",
    "StartDateTime": "2022-06-15T16:20:00",
    "WebId": 90931,
    "Status": 1
  },
  {
    "StatusHeading": "Removing hazards and diagnosing network fault",
    "Area": "Collaroy",
    "Cause": "Under investigation",
    "Customers": "41",
    "EstRestTime": "2022-06-15T21:00:00",
    "StartDateTime": "2022-06-15T16:30:00",
    "WebId": 90932,
    "Status": 1
  },
  {
    "StatusHeading": "Removing hazards and diagnosing network fault",
    "Area": "Punchbowl",
    "Cause": "Overhead line damage",
    "Customers": "103",
    "EstRestTime": "2022-06-15T20:00:00",
    "StartDateTime": "2022-06-15T17:40:00",
    "WebId": 90933,
    "Status": 1
  },
  {
    "StatusHeading": "Removing hazards and diagnosing network fault",
    "Area": "Milperra, East Hills, Panania",
    "Cause": "Under investigation",
    "Customers": "1167",
    "EstRestTime": "2022-06-15T20:00:00",
    "StartDateTime": "2022-06-15T17:40:00",
    "WebId": 90934,
    "Status": 1
  },
  {
    "StatusHeading": "Removing hazards and diagnosing network fault",
    "Area": "Lindfield",
    "Cause": "Under investigation",
    "Customers": "99",
    "EstRestTime": "2022-06-15T20:30:00",
    "StartDateTime": "2022-06-15T18:05:00",
    "WebId": 90935,
    "Status": 1
  },
  {
    "StatusHeading": "Removing hazards and diagnosing network fault",
    "Area": "Punchbowl",
    "Cause": "Overhead line damage",
    "Customers": "69",
    "EstRestTime": "2022-06-15T20:30:00",
    "StartDateTime": "2022-06-15T18:25:00",
    "WebId": 90936,
    "Status": 1
  },
  {
    "StatusHeading": "Outage Reported",
    "Area": "Punchbowl",
    "Cause": "Under investigation",
    "Customers": "30",
    "EstRestTime": "2022-06-15T21:00:00",
    "StartDateTime": "2022-06-15T18:40:00",
    "WebId": 90937,
    "Status": 0
  }
]
