[
  {
    "StatusHeading": "Removing hazards and diagnosing network fault",
    "Area": "Buchanan, Heddon Greta",
    "Cause": "Under investigation",
    "Customers": "less than 10",
    "EstRestTime": "2022-06-23T20:00:00",
    "StartDateTime": "2022-06-23T17:35:00",
    "WebId": 91015,
    "Status": 1
  },
  {
    "StatusHeading": "Outage Reported",
    "Area": "Centennial Park, Paddington",
    "Cause": "Under investigation",
    "Customers": "141",
    "EstRestTime": "2022-06-23T21:30:00",
    "StartDateTime": "2022-06-23T19:10:00",
    "WebId": 91016,
    "Status": 0
  }
]
