[
  {
    "StatusHeading": "Known power outage - working to restore power",
    "Area": "Bankstown",
    "Cause": "Under investigation",
    "Customers": "less than 10",
    "EstRestTime": "2023-12-05T14:30:00",
    "StartDateTime": "2023-12-05T12:20:00",
    "WebId": 98827,
    "Status": 2
  },
  {
    "StatusHeading": "Known power outage - working to restore power",
    "Area": "Double Bay",
    "Cause": "Under investigation",
    "Customers": "53",
    "EstRestTime": "2023-12-08T00:00:00",
    "StartDateTime": "2023-12-07T20:10:00",
    "WebId": 98865,
    "Status": 1
  }
]
