[
  {
    "StatusHeading": "Removing hazards and diagnosing network fault",
    "Area": "Bankstown",
    "Cause": "Under investigation",
    "Customers": "101",
    "EstRestTime": "2023-03-04T22:30:00",
    "StartDateTime": "2023-03-04T17:30:00",
    "WebId": 95490,
    "Status": 1
  },
  {
    "StatusHeading": "Removing hazards and diagnosing network fault",
    "Area": "Hamilton",
    "Cause": "Under investigation",
    "Customers": "less than 10",
    "EstRestTime": "2023-03-04T22:30:00",
    "StartDateTime": "2023-03-04T19:50:00",
    "WebId": 95492,
    "Status": 1
  },
  {
    "StatusHeading": "Removing hazards and diagnosing network fault",
    "Area": "Tacoma, Wyong",
    "Cause": "Under investigation",
    "Customers": "33",
    "EstRestTime": "2023-03-04T22:30:00",
    "StartDateTime": "2023-03-04T20:00:00",
    "WebId": 95493,
    "Status": 1
  }
]
