[
  {
    "StatusHeading": "Known power outage - working to restore power",
    "Area": "Caringbah, Caringbah South, Lilli Pilli, Port Hacking, Royal National Park, Warumbul",
    "Cause": "Under investigation",
    "Customers": "1063",
    "EstRestTime": "2025-08-19T14:30:00",
    "StartDateTime": "2025-08-19T12:00:00",
    "WebId": 145752,
    "Status": 1
  },
  {
    "StatusHeading": "Known power outage - working to restore power",
    "Area": "Cooranbong, Morisset",
    "Cause": "Vehicle striking pole",
    "Customers": "169",
    "EstRestTime": "2025-08-19T14:30:00",
    "StartDateTime": "2025-08-19T12:20:00",
    "WebId": 145739,
    "Status": 1
  }
]