[
  {
    "StatusHeading": "Known power outage - working to restore power",
    "Area": "Manly",
    "Cause": "Under investigation",
    "Customers": "less than 10",
    "EstRestTime": "2023-07-18T15:30:00",
    "StartDateTime": "2023-07-18T13:00:00",
    "WebId": 97061,
    "Status": 2
  },
  {
    "StatusHeading": "Known power outage - working to restore power",
    "Area": "Pymble",
    "Cause": "Under investigation",
    "Customers": "43",
    "EstRestTime": "2023-07-21T19:00:00",
    "StartDateTime": "2023-07-21T16:35:00",
    "WebId": 97083,
    "Status": 1
  },
  {
    "StatusHeading": "Known power outage - working to restore power",
    "Area": "Engadine",
    "Cause": "Under investigation",
    "Customers": "49",
    "EstRestTime": "2023-07-21T21:00:00",
    "StartDateTime": "2023-07-21T18:40:00",
    "WebId": 97084,
    "Status": 1
  },
  {
    "StatusHeading": "Known power outage - working to restore power",
    "Area": "Eastwood, Epping, Denistone, West Ryde, Marsfield",
    "Cause": "Under investigation",
    "Customers": "3082",
    "EstRestTime": "2023-07-21T21:30:00",
    "StartDateTime": "2023-07-21T19:10:00",
    "WebId": 97085,
    "Status": 1
  },
  {
    "StatusHeading": "Known power outage - working to restore power",
    "Area": "Eastwood, West Ryde, Denistone, Denistone East",
    "Cause": "Under investigation",
    "Customers": "828",
    "EstRestTime": "2023-07-21T21:30:00",
    "StartDateTime": "2023-07-21T19:10:00",
    "WebId": 97086,
    "Status": 1
  }
]
