[
  {
    "StatusHeading": "Removing hazards and diagnosing network fault",
    "Area": "Waitara",
    "Cause": "Under investigation",
    "Customers": "less than 10",
    "EstRestTime": "2022-06-24T18:00:00",
    "StartDateTime": "2022-06-24T12:40:00",
    "WebId": 91026,
    "Status": 1
  },
  {
    "StatusHeading": "Outage Reported",
    "Area": "Hurstville, Allawah, South Hurstville",
    "Cause": "Under investigation",
    "Customers": "96",
    "EstRestTime": "2022-06-24T17:00:00",
    "StartDateTime": "2022-06-24T14:30:00",
    "WebId": 91027,
    "Status": 0
  }
]
