[
  {
    "StatusHeading": "Ongoing network repairs",
    "Area": "Singleton Heights",
    "Cause": "Under investigation",
    "Customers": "less than 10",
    "EstRestTime": "2022-12-24T10:30:00",
    "StartDateTime": "2022-12-24T00:35:00",
    "WebId": 93868,
    "Status": 2
  },
  {
    "StatusHeading": "Removing hazards and diagnosing network fault",
    "Area": "Berkeley Vale, Killarney Vale, Tumbi Umbi",
    "Cause": "Under investigation",
    "Customers": "830",
    "EstRestTime": "2022-12-25T03:30:00",
    "StartDateTime": "2022-12-25T01:00:00",
    "WebId": 93879,
    "Status": 1
  },
  {
    "StatusHeading": "Removing hazards and diagnosing network fault",
    "Area": "Salt Ash, Williamtown, Bobs Farm",
    "Cause": "Under investigation",
    "Customers": "698",
    "EstRestTime": "2022-12-25T03:30:00",
    "StartDateTime": "2022-12-25T01:05:00",
    "WebId": 93880,
    "Status": 1
  }
]
