[
  {
    "StatusHeading": "Ongoing network repairs",
    "Area": "Cronulla, Woolooware, Burraneer, Caringbah",
    "Cause": "Trees over power lines",
    "Customers": "49",
    "EstRestTime": "2023-02-04T20:00:00",
    "StartDateTime": "2023-02-04T12:05:00",
    "WebId": 94529,
    "Status": 2
  },
  {
    "StatusHeading": "Ongoing network repairs",
    "Area": "Hurstville",
    "Cause": "Vehicle Striking Pole",
    "Customers": "52",
    "EstRestTime": "2023-02-04T20:00:00",
    "StartDateTime": "2023-02-04T13:05:00",
    "WebId": 94533,
    "Status": 2
  },
  {
    "StatusHeading": "Removing hazards and diagnosing network fault",
    "Area": "Botany, Pagewood, Banksmeadow",
    "Cause": "Under investigation",
    "Customers": "39",
    "EstRestTime": "2023-02-04T20:30:00",
    "StartDateTime": "2023-02-04T17:55:00",
    "WebId": 94538,
    "Status": 1
  }
]
