[
  {
    "StatusHeading": "Known power outage - working to restore power",
    "Area": "Newport",
    "Cause": "Underground cable fault",
    "Customers": "19",
    "EstRestTime": "2024-05-04T19:30:00",
    "StartDateTime": "2024-05-04T12:00:00",
    "WebId": 101769,
    "Status": 2
  },
  {
    "StatusHeading": "Known power outage - working to restore power",
    "Area": "Strathfield",
    "Cause": "Under investigation",
    "Customers": "36",
    "EstRestTime": "2024-05-04T18:30:00",
    "StartDateTime": "2024-05-04T14:30:00",
    "WebId": 101771,
    "Status": 1
  },
  {
    "StatusHeading": "Known power outage - working to restore power",
    "Area": "Umina Beach",
    "Cause": "Under investigation",
    "Customers": "12",
    "EstRestTime": "2024-05-04T19:30:00",
    "StartDateTime": "2024-05-04T17:05:00",
    "WebId": 101772,
    "Status": 1
  },
  {
    "StatusHeading": "Known power outage - working to restore power",
    "Area": "Umina Beach",
    "Cause": "Under investigation",
    "Customers": "31",
    "EstRestTime": "2024-05-04T19:30:00",
    "StartDateTime": "2024-05-04T17:00:00",
    "WebId": 101773,
    "Status": 1
  },
  {
    "StatusHeading": "Known power outage - working to restore power",
    "Area": "Kirribilli",
    "Cause": "Underground cable fault",
    "Customers": "55",
    "EstRestTime": "2024-05-04T20:30:00",
    "StartDateTime": "2024-05-04T16:55:00",
    "WebId": 101774,
    "Status": 1
  }
]
