[
  {
    "StatusHeading": "Known power outage - working to restore power",
    "Area": "Brighton-Le-Sands",
    "Cause": "Under investigation",
    "Customers": "30",
    "EstRestTime": "2025-05-29T10:30:00",
    "StartDateTime": "2025-05-29T08:15:00",
    "WebId": 124086,
    "Status": 2
  },
  {
    "StatusHeading": "Known power outage - working to restore power",
    "Area": "Tighes Hill",
    "Cause": "Under investigation",
    "Customers": "68",
    "EstRestTime": "2025-06-24T22:30:00",
    "StartDateTime": "2025-06-24T18:15:00",
    "WebId": 129327,
    "Status": 2
  },
  {
    "StatusHeading": "Known power outage - working to restore power",
    "Area": "Somersby",
    "Cause": "Severe weather conditions",
    "Customers": "12",
    "EstRestTime": "2025-07-02T16:00:00",
    "StartDateTime": "2025-07-01T14:05:00",
    "WebId": 132218,
    "Status": 2
  },
  {
    "StatusHeading": "Known power outage - working to restore power",
    "Area": "Somersby",
    "Cause": "Severe weather conditions",
    "Customers": "152",
    "EstRestTime": "2025-07-02T16:00:00",
    "StartDateTime": "2025-07-01T11:00:00",
    "WebId": 132220,
    "Status": 2
  },
  {
    "StatusHeading": "Known power outage - working to restore power",
    "Area": "Brooklyn, Cheero Point, Mooney Mooney",
    "Cause": "Severe weather conditions",
    "Customers": "242",
    "EstRestTime": "2025-07-02T16:00:00",
    "StartDateTime": "2025-07-01T12:50:00",
    "WebId": 132297,
    "Status": 2
  },
  {
    "StatusHeading": "Known power outage - working to restore power",
    "Area": "Mosman",
    "Cause": "Under investigation",
    "Customers": "less than 10",
    "EstRestTime": "2025-07-01T18:30:00",
    "StartDateTime": "2025-07-01T12:05:00",
    "WebId": 132313,
    "Status": 2
  },
  {
    "StatusHeading": "Known power outage - working to restore power",
    "Area": "Allambie Heights",
    "Cause": "Under investigation",
    "Customers": "55",
    "EstRestTime": "2025-07-01T15:30:00",
    "StartDateTime": "2025-07-01T12:55:00",
    "WebId": 132326,
    "Status": 2
  },
  {
    "StatusHeading": "Known power outage - working to restore power",
    "Area": "Central Mangrove, Kulnura, Mangrove Mountain, Peats Ridge",
    "Cause": "Severe weather conditions",
    "Customers": "160",
    "EstRestTime": "2025-07-02T16:00:00",
    "StartDateTime": "2025-07-01T13:40:00",
    "WebId": 132343,
    "Status": 2
  },
  {
    "StatusHeading": "Known power outage - working to restore power",
    "Area": "Ourimbah, Somersby",
    "Cause": "Severe weather conditions",
    "Customers": "61",
    "EstRestTime": "2025-07-02T16:00:00",
    "StartDateTime": "2025-07-01T14:00:00",
    "WebId": 132371,
    "Status": 2
  },
  {
    "StatusHeading": "Known power outage - working to restore power",
    "Area": "Belrose",
    "Cause": "Severe weather conditions",
    "Customers": "42",
    "EstRestTime": "2025-07-02T16:00:00",
    "StartDateTime": "2025-07-01T19:05:00",
    "WebId": 132380,
    "Status": 2
  },
  {
    "StatusHeading": "Known power outage - working to restore power",
    "Area": "Holgate, Matcham, Tumbi Umbi",
    "Cause": "Severe weather conditions",
    "Customers": "26",
    "EstRestTime": "2025-07-02T16:00:00",
    "StartDateTime": "2025-07-01T14:20:00",
    "WebId": 132389,
    "Status": 2
  },
  {
    "StatusHeading": "Known power outage - working to restore power",
    "Area": "Central Mangrove, Mangrove Mountain, Somersby",
    "Cause": "Severe weather conditions",
    "Customers": "98",
    "EstRestTime": "2025-07-02T16:00:00",
    "StartDateTime": "2025-07-01T14:20:00",
    "WebId": 132394,
    "Status": 2
  },
  {
    "StatusHeading": "Known power outage - working to restore power",
    "Area": "Darlinghurst, Erina, Erina Heights, Holgate, Matcham, Mount Elliot, Terrigal, Wamberal",
    "Cause": "Severe weather conditions",
    "Customers": "50",
    "EstRestTime": "2025-07-02T16:00:00",
    "StartDateTime": "2025-07-01T14:40:00",
    "WebId": 132410,
    "Status": 2
  },
  {
    "StatusHeading": "Known power outage - working to restore power",
    "Area": "Balgowlah",
    "Cause": "Severe weather conditions",
    "Customers": "43",
    "EstRestTime": "2025-07-02T16:00:00",
    "StartDateTime": "2025-07-01T14:10:00",
    "WebId": 132412,
    "Status": 2
  },
  {
    "StatusHeading": "Known power outage - working to restore power",
    "Area": "Dooralong, Lemon Tree",
    "Cause": "Severe weather conditions",
    "Customers": "85",
    "EstRestTime": "2025-07-02T16:00:00",
    "StartDateTime": "2025-07-01T14:45:00",
    "WebId": 132421,
    "Status": 2
  },
  {
    "StatusHeading": "Known power outage - working to restore power",
    "Area": "Kulnura",
    "Cause": "Severe weather conditions",
    "Customers": "67",
    "EstRestTime": "2025-07-02T16:00:00",
    "StartDateTime": "2025-07-01T14:45:00",
    "WebId": 132422,
    "Status": 2
  },
  {
    "StatusHeading": "Known power outage - working to restore power",
    "Area": "Beresfield, Millers Forest, Tarro, Thornton, Woodberry",
    "Cause": "Under investigation",
    "Customers": "less than 10",
    "EstRestTime": "2025-07-02T16:00:00",
    "StartDateTime": "2025-07-01T14:50:00",
    "WebId": 132428,
    "Status": 2
  },
  {
    "StatusHeading": "Known power outage - working to restore power",
    "Area": "Ourimbah, Palm Grove",
    "Cause": "Severe weather conditions",
    "Customers": "106",
    "EstRestTime": "2025-07-02T16:00:00",
    "StartDateTime": "2025-07-01T14:55:00",
    "WebId": 132460,
    "Status": 2
  },
  {
    "StatusHeading": "Known power outage - working to restore power",
    "Area": "Cooranbong, Martinsville",
    "Cause": "Under investigation",
    "Customers": "347",
    "EstRestTime": "2025-07-02T16:00:00",
    "StartDateTime": "2025-07-01T15:00:00",
    "WebId": 132468,
    "Status": 2
  },
  {
    "StatusHeading": "Known power outage - working to restore power",
    "Area": "Cooranbong, Dora Creek, Martinsville, Morisset",
    "Cause": "Under investigation",
    "Customers": "454",
    "EstRestTime": "2025-07-02T16:00:00",
    "StartDateTime": "2025-07-01T15:00:00",
    "WebId": 132478,
    "Status": 2
  },
  {
    "StatusHeading": "Known power outage - working to restore power",
    "Area": "Sylvania",
    "Cause": "Under investigation",
    "Customers": "less than 10",
    "EstRestTime": "2025-07-01T20:30:00",
    "StartDateTime": "2025-07-01T14:45:00",
    "WebId": 132490,
    "Status": 2
  },
  {
    "StatusHeading": "Known power outage - working to restore power",
    "Area": "Hurstville",
    "Cause": "Under investigation",
    "Customers": "13",
    "EstRestTime": "2025-07-01T20:30:00",
    "StartDateTime": "2025-07-01T12:55:00",
    "WebId": 132491,
    "Status": 2
  },
  {
    "StatusHeading": "Known power outage - working to restore power",
    "Area": "Kulnura, Wyong Creek",
    "Cause": "Severe weather conditions",
    "Customers": "60",
    "EstRestTime": "2025-07-02T16:00:00",
    "StartDateTime": "2025-07-01T15:10:00",
    "WebId": 132503,
    "Status": 2
  },
  {
    "StatusHeading": "Known power outage - working to restore power",
    "Area": "Bushells Ridge, Jilliby, Kiar, Mandalong, Morisset, Wyee",
    "Cause": "Under investigation",
    "Customers": "1317",
    "EstRestTime": "2025-07-02T16:00:00",
    "StartDateTime": "2025-07-01T15:15:00",
    "WebId": 132527,
    "Status": 2
  },
  {
    "StatusHeading": "Known power outage - working to restore power",
    "Area": "Cooranbong, Dooralong, Mandalong, Morisset",
    "Cause": "Under investigation",
    "Customers": "858",
    "EstRestTime": "2025-07-02T16:00:00",
    "StartDateTime": "2025-07-01T15:30:00",
    "WebId": 132583,
    "Status": 2
  },
  {
    "StatusHeading": "Known power outage - working to restore power",
    "Area": "Eraring, Myuna Bay, Wangi Wangi",
    "Cause": "Under investigation",
    "Customers": "132",
    "EstRestTime": "2025-07-02T16:00:00",
    "StartDateTime": "2025-07-01T15:30:00",
    "WebId": 132585,
    "Status": 2
  },
  {
    "StatusHeading": "Known power outage - working to restore power",
    "Area": "Berkeley Vale, Glenning Valley",
    "Cause": "Severe weather conditions",
    "Customers": "244",
    "EstRestTime": "2025-07-02T16:00:00",
    "StartDateTime": "2025-07-01T15:35:00",
    "WebId": 132597,
    "Status": 2
  },
  {
    "StatusHeading": "Known power outage - working to restore power",
    "Area": "Cooranbong, Freemans Waterhole",
    "Cause": "Under investigation",
    "Customers": "120",
    "EstRestTime": "2025-07-02T16:00:00",
    "StartDateTime": "2025-07-01T15:35:00",
    "WebId": 132598,
    "Status": 2
  },
  {
    "StatusHeading": "Known power outage - working to restore power",
    "Area": "Killarney Vale",
    "Cause": "Severe weather conditions",
    "Customers": "27",
    "EstRestTime": "2025-07-02T16:00:00",
    "StartDateTime": "2025-07-01T15:10:00",
    "WebId": 132600,
    "Status": 2
  },
  {
    "StatusHeading": "Known power outage - working to restore power",
    "Area": "Sylvania",
    "Cause": "Under investigation",
    "Customers": "11",
    "EstRestTime": "2025-07-01T21:00:00",
    "StartDateTime": "2025-07-01T13:40:00",
    "WebId": 132629,
    "Status": 2
  },
  {
    "StatusHeading": "Known power outage - working to restore power",
    "Area": "Congewai, Paxton",
    "Cause": "Under investigation",
    "Customers": "less than 10",
    "EstRestTime": "2025-07-02T16:00:00",
    "StartDateTime": "2025-07-01T16:35:00",
    "WebId": 132643,
    "Status": 2
  },
  {
    "StatusHeading": "Known power outage - working to restore power",
    "Area": "Bateau Bay, Berkeley Vale, Killarney Vale, Long Jetty, the Entrance, Toowoon Bay",
    "Cause": "Severe weather conditions",
    "Customers": "676",
    "EstRestTime": "2025-07-02T16:00:00",
    "StartDateTime": "2025-07-01T15:55:00",
    "WebId": 132673,
    "Status": 2
  },
  {
    "StatusHeading": "Known power outage - working to restore power",
    "Area": "Buttaba",
    "Cause": "Under investigation",
    "Customers": "45",
    "EstRestTime": "2025-07-02T16:00:00",
    "StartDateTime": "2025-07-01T16:00:00",
    "WebId": 132682,
    "Status": 2
  },
  {
    "StatusHeading": "Known power outage - working to restore power",
    "Area": "Birrong",
    "Cause": "Under investigation",
    "Customers": "less than 10",
    "EstRestTime": "2025-07-01T21:30:00",
    "StartDateTime": "2025-07-01T06:45:00",
    "WebId": 132690,
    "Status": 2
  },
  {
    "StatusHeading": "Known power outage - working to restore power",
    "Area": "Cooranbong, Dora Creek",
    "Cause": "Under investigation",
    "Customers": "469",
    "EstRestTime": "2025-07-02T16:00:00",
    "StartDateTime": "2025-07-01T16:05:00",
    "WebId": 132707,
    "Status": 2
  },
  {
    "StatusHeading": "Known power outage - working to restore power",
    "Area": "Dooralong, Durren Durren, Jilliby, Little Jilliby",
    "Cause": "Severe weather conditions",
    "Customers": "295",
    "EstRestTime": "2025-07-02T16:00:00",
    "StartDateTime": "2025-07-01T16:10:00",
    "WebId": 132718,
    "Status": 2
  },
  {
    "StatusHeading": "Known power outage - working to restore power",
    "Area": "Aberdare, Cessnock, Elrington, Kearsley",
    "Cause": "Under investigation",
    "Customers": "41",
    "EstRestTime": "2025-07-02T16:00:00",
    "StartDateTime": "2025-07-01T16:40:00",
    "WebId": 132735,
    "Status": 2
  },
  {
    "StatusHeading": "Known power outage - working to restore power",
    "Area": "Campvale, Medowie",
    "Cause": "Under investigation",
    "Customers": "less than 10",
    "EstRestTime": "2025-07-02T16:00:00",
    "StartDateTime": "2025-07-01T16:15:00",
    "WebId": 132737,
    "Status": 2
  },
  {
    "StatusHeading": "Known power outage - working to restore power",
    "Area": "Kariong, Somersby",
    "Cause": "Severe weather conditions",
    "Customers": "67",
    "EstRestTime": "2025-07-02T16:00:00",
    "StartDateTime": "2025-07-01T16:15:00",
    "WebId": 132748,
    "Status": 2
  },
  {
    "StatusHeading": "Known power outage - working to restore power",
    "Area": "Ashfield",
    "Cause": "Under investigation",
    "Customers": "25",
    "EstRestTime": "2025-07-01T21:30:00",
    "StartDateTime": "2025-07-01T15:40:00",
    "WebId": 132768,
    "Status": 2
  },
  {
    "StatusHeading": "Known power outage - working to restore power",
    "Area": "Kincumber, Macmasters Beach",
    "Cause": "Severe weather conditions",
    "Customers": "74",
    "EstRestTime": "2025-07-02T16:00:00",
    "StartDateTime": "2025-07-01T16:25:00",
    "WebId": 132773,
    "Status": 2
  },
  {
    "StatusHeading": "Known power outage - working to restore power",
    "Area": "Aberdare, Broke, Bucketty, Cedar Creek, Congewai, Dairy Arm, Ellalong, Fernances Crossing, Greta Main, Kitchener, Kulnura, Laguna, Millfield, Mount View, Murrays Run, Paxton, Paynes Crossing, Pelton, Sweetmans Creek, Via Laguna, Via Wollombi, Watagan, Wattagan, Wollombi, Yango Creek",
    "Cause": "Under investigation",
    "Customers": "1833",
    "EstRestTime": "2025-07-02T16:00:00",
    "StartDateTime": "2025-07-01T16:35:00",
    "WebId": 132796,
    "Status": 2
  },
  {
    "StatusHeading": "Known power outage - working to restore power",
    "Area": "Tumbi Umbi, Wamberal",
    "Cause": "Severe weather conditions",
    "Customers": "57",
    "EstRestTime": "2025-07-02T16:00:00",
    "StartDateTime": "2025-07-01T16:40:00",
    "WebId": 132807,
    "Status": 2
  },
  {
    "StatusHeading": "Known power outage - working to restore power",
    "Area": "Lisarow, Mount Elliot, Wyoming",
    "Cause": "Severe weather conditions",
    "Customers": "less than 10",
    "EstRestTime": "2025-07-02T16:00:00",
    "StartDateTime": "2025-07-01T16:45:00",
    "WebId": 132816,
    "Status": 2
  },
  {
    "StatusHeading": "Known power outage - working to restore power",
    "Area": "Mona Vale",
    "Cause": "Severe weather conditions",
    "Customers": "62",
    "EstRestTime": "2025-07-02T16:00:00",
    "StartDateTime": "2025-07-01T17:50:00",
    "WebId": 132850,
    "Status": 2
  },
  {
    "StatusHeading": "Known power outage - working to restore power",
    "Area": "Chain Valley Bay",
    "Cause": "Severe weather conditions",
    "Customers": "32",
    "EstRestTime": "2025-07-02T16:00:00",
    "StartDateTime": "2025-07-01T12:55:00",
    "WebId": 132875,
    "Status": 2
  },
  {
    "StatusHeading": "Known power outage - working to restore power",
    "Area": "Bateau Bay",
    "Cause": "Severe weather conditions",
    "Customers": "41",
    "EstRestTime": "2025-07-02T16:00:00",
    "StartDateTime": "2025-07-01T17:05:00",
    "WebId": 132901,
    "Status": 2
  },
  {
    "StatusHeading": "Known power outage - working to restore power",
    "Area": "Palm Beach",
    "Cause": "Severe weather conditions",
    "Customers": "26",
    "EstRestTime": "2025-07-02T16:00:00",
    "StartDateTime": "2025-07-01T18:10:00",
    "WebId": 132906,
    "Status": 2
  },
  {
    "StatusHeading": "Known power outage - working to restore power",
    "Area": "Glenning Valley, Tumbi Umbi",
    "Cause": "Severe weather conditions",
    "Customers": "15",
    "EstRestTime": "2025-07-02T16:00:00",
    "StartDateTime": "2025-07-01T16:50:00",
    "WebId": 132911,
    "Status": 2
  },
  {
    "StatusHeading": "Known power outage - working to restore power",
    "Area": "Springfield",
    "Cause": "Severe weather conditions",
    "Customers": "less than 10",
    "EstRestTime": "2025-07-02T16:00:00",
    "StartDateTime": "2025-07-01T16:20:00",
    "WebId": 132919,
    "Status": 2
  },
  {
    "StatusHeading": "Known power outage - working to restore power",
    "Area": "Dora Creek",
    "Cause": "Under investigation",
    "Customers": "18",
    "EstRestTime": "2025-07-02T16:00:00",
    "StartDateTime": "2025-07-01T16:05:00",
    "WebId": 132928,
    "Status": 2
  },
  {
    "StatusHeading": "Known power outage - working to restore power",
    "Area": "Holgate, Lisarow, Mount Elliot, Tumbi Umbi",
    "Cause": "Severe weather conditions",
    "Customers": "48",
    "EstRestTime": "2025-07-02T16:00:00",
    "StartDateTime": "2025-07-01T17:50:00",
    "WebId": 132933,
    "Status": 2
  },
  {
    "StatusHeading": "Known power outage - working to restore power",
    "Area": "Carey Bay, Kilaben Bay, Toronto",
    "Cause": "Under investigation",
    "Customers": "508",
    "EstRestTime": "2025-07-02T16:00:00",
    "StartDateTime": "2025-07-01T17:55:00",
    "WebId": 132935,
    "Status": 2
  },
  {
    "StatusHeading": "Known power outage - working to restore power",
    "Area": "Wallarah, Warnervale, Wyong",
    "Cause": "Severe weather conditions",
    "Customers": "179",
    "EstRestTime": "2025-07-02T16:00:00",
    "StartDateTime": "2025-07-01T18:10:00",
    "WebId": 132964,
    "Status": 2
  },
  {
    "StatusHeading": "Known power outage - working to restore power",
    "Area": "Cooranbong, Martinsville",
    "Cause": "Under investigation",
    "Customers": "954",
    "EstRestTime": "2025-07-02T16:00:00",
    "StartDateTime": "2025-07-01T18:15:00",
    "WebId": 132968,
    "Status": 2
  },
  {
    "StatusHeading": "Known power outage - working to restore power",
    "Area": "Medowie",
    "Cause": "Under investigation",
    "Customers": "43",
    "EstRestTime": "2025-07-02T16:00:00",
    "StartDateTime": "2025-07-01T18:15:00",
    "WebId": 132969,
    "Status": 2
  },
  {
    "StatusHeading": "Known power outage - working to restore power",
    "Area": "Point Frederick",
    "Cause": "Under investigation",
    "Customers": "13",
    "EstRestTime": "2025-07-02T06:30:00",
    "StartDateTime": "2025-07-01T18:20:00",
    "WebId": 132981,
    "Status": 2
  },
  {
    "StatusHeading": "Known power outage - working to restore power",
    "Area": "Bar Beach, Cooks Hill, Merewether, Newcastle, Newcastle West, the Hill, the Junction",
    "Cause": "Under investigation",
    "Customers": "2428",
    "EstRestTime": "2025-07-02T16:00:00",
    "StartDateTime": "2025-07-01T18:30:00",
    "WebId": 132988,
    "Status": 2
  },
  {
    "StatusHeading": "Known power outage - working to restore power",
    "Area": "Toronto",
    "Cause": "Under investigation",
    "Customers": "69",
    "EstRestTime": "2025-07-02T12:30:00",
    "StartDateTime": "2025-07-01T18:40:00",
    "WebId": 133004,
    "Status": 2
  },
  {
    "StatusHeading": "Known power outage - working to restore power",
    "Area": "Church Point, McCarrs Creek",
    "Cause": "Severe weather conditions",
    "Customers": "36",
    "EstRestTime": "2025-07-02T16:00:00",
    "StartDateTime": "2025-07-01T19:25:00",
    "WebId": 133024,
    "Status": 2
  },
  {
    "StatusHeading": "Known power outage - working to restore power",
    "Area": "Woongarrah",
    "Cause": "Severe weather conditions",
    "Customers": "less than 10",
    "EstRestTime": "2025-07-02T16:00:00",
    "StartDateTime": "2025-07-01T18:55:00",
    "WebId": 133033,
    "Status": 2
  },
  {
    "StatusHeading": "Known power outage - working to restore power",
    "Area": "Terrey Hills",
    "Cause": "Severe weather conditions",
    "Customers": "70",
    "EstRestTime": "2025-07-02T16:00:00",
    "StartDateTime": "2025-07-02T01:10:00",
    "WebId": 133063,
    "Status": 1
  },
  {
    "StatusHeading": "Known power outage - working to restore power",
    "Area": "Bateau Bay, Killarney Vale",
    "Cause": "Under investigation",
    "Customers": "136",
    "EstRestTime": "2025-07-02T16:00:00",
    "StartDateTime": "2025-07-01T19:25:00",
    "WebId": 133089,
    "Status": 2
  },
  {
    "StatusHeading": "Known power outage - working to restore power",
    "Area": "Cooranbong, Dora Creek, Morisset",
    "Cause": "Under investigation",
    "Customers": "63",
    "EstRestTime": "2025-07-02T16:00:00",
    "StartDateTime": "2025-07-01T19:30:00",
    "WebId": 133093,
    "Status": 2
  },
  {
    "StatusHeading": "Known power outage - working to restore power",
    "Area": "Wyoming",
    "Cause": "Under investigation",
    "Customers": "38",
    "EstRestTime": "2025-07-02T16:00:00",
    "StartDateTime": "2025-07-01T19:20:00",
    "WebId": 133119,
    "Status": 2
  },
  {
    "StatusHeading": "Known power outage - working to restore power",
    "Area": "Balickera, Eagleton, East Seaham, Ferodale, Kings Hill, Medowie, Raymond Terrace, Twelve Mile Creek",
    "Cause": "Under investigation",
    "Customers": "less than 10",
    "EstRestTime": "2025-07-02T16:00:00",
    "StartDateTime": "2025-07-01T20:10:00",
    "WebId": 133123,
    "Status": 2
  },
  {
    "StatusHeading": "Known power outage - working to restore power",
    "Area": "Crows Nest, Greenwich, St Leonards",
    "Cause": "Under investigation",
    "Customers": "98",
    "EstRestTime": "2025-07-02T16:00:00",
    "StartDateTime": "2025-07-02T01:40:00",
    "WebId": 133168,
    "Status": 1
  },
  {
    "StatusHeading": "Known power outage - working to restore power",
    "Area": "Frenchs Forest",
    "Cause": "Under investigation",
    "Customers": "44",
    "EstRestTime": "2025-07-02T16:00:00",
    "StartDateTime": "2025-07-02T00:15:00",
    "WebId": 133183,
    "Status": 1
  },
  {
    "StatusHeading": "Known power outage - working to restore power",
    "Area": "Bayview, Church Point, Elvina Bay, Ingleside, McCarrs Creek, Scotland Island",
    "Cause": "Under investigation",
    "Customers": "693",
    "EstRestTime": "2025-07-02T16:00:00",
    "StartDateTime": "2025-07-01T22:50:00",
    "WebId": 133186,
    "Status": 2
  },
  {
    "StatusHeading": "Known power outage - working to restore power",
    "Area": "Gwandalan",
    "Cause": "Under investigation",
    "Customers": "103",
    "EstRestTime": "2025-07-02T16:00:00",
    "StartDateTime": "2025-07-01T12:55:00",
    "WebId": 133191,
    "Status": 2
  },
  {
    "StatusHeading": "Known power outage - working to restore power",
    "Area": "Baerami, Kerrabee, Murrumbo",
    "Cause": "Under investigation",
    "Customers": "11",
    "EstRestTime": "2025-07-02T16:00:00",
    "StartDateTime": "2025-07-01T23:45:00",
    "WebId": 133198,
    "Status": 1
  },
  {
    "StatusHeading": "Known power outage - working to restore power",
    "Area": "Mona Vale",
    "Cause": "Under investigation",
    "Customers": "41",
    "EstRestTime": "2025-07-02T02:00:00",
    "StartDateTime": "2025-07-01T23:45:00",
    "WebId": 133200,
    "Status": 1
  },
  {
    "StatusHeading": "Known power outage - working to restore power",
    "Area": "Davistown, Saratoga, Yattalunga",
    "Cause": "Under investigation",
    "Customers": "694",
    "EstRestTime": "2025-07-02T16:00:00",
    "StartDateTime": "2025-07-02T00:35:00",
    "WebId": 133210,
    "Status": 1
  },
  {
    "StatusHeading": "Known power outage - working to restore power",
    "Area": "Blue Haven",
    "Cause": "Under investigation",
    "Customers": "27",
    "EstRestTime": "2025-07-02T16:00:00",
    "StartDateTime": "2025-07-01T16:45:00",
    "WebId": 133214,
    "Status": 2
  },
  {
    "StatusHeading": "Known power outage - working to restore power",
    "Area": "Blue Haven",
    "Cause": "Under investigation",
    "Customers": "24",
    "EstRestTime": "2025-07-02T16:00:00",
    "StartDateTime": "2025-07-01T16:45:00",
    "WebId": 133215,
    "Status": 2
  },
  {
    "StatusHeading": "Known power outage - working to restore power",
    "Area": "Auburn",
    "Cause": "Under investigation",
    "Customers": "661",
    "EstRestTime": "2025-07-02T16:00:00",
    "StartDateTime": "2025-07-02T01:30:00",
    "WebId": 133222,
    "Status": 1
  },
  {
    "StatusHeading": "Known power outage - working to restore power",
    "Area": "Concord West, Rhodes",
    "Cause": "Under investigation",
    "Customers": "424",
    "EstRestTime": "2025-07-02T16:00:00",
    "StartDateTime": "2025-07-02T01:40:00",
    "WebId": 133226,
    "Status": 1
  },
  {
    "StatusHeading": "Known power outage",
    "Area": "Berowra, Cowan",
    "Cause": "Under investigation",
    "Customers": "32",
    "EstRestTime": "2025-07-02T16:00:00",
    "StartDateTime": "2025-07-02T02:35:00",
    "WebId": 133232,
    "Status": 0
  },
  {
    "StatusHeading": "Known power outage",
    "Area": "Mandalong",
    "Cause": "Under investigation",
    "Customers": "less than 10",
    "EstRestTime": "2025-07-02T16:00:00",
    "StartDateTime": "2025-07-02T02:30:00",
    "WebId": 133236,
    "Status": 0
  }
]