[
  {
    "StatusHeading": "Known power outage - working to restore power",
    "Area": "Budgewoi",
    "Cause": "Under investigation",
    "Customers": "74",
    "EstRestTime": "2024-01-07T14:00:00",
    "StartDateTime": "2024-01-07T11:45:00",
    "WebId": 99569,
    "Status": 2
  },
  {
    "StatusHeading": "Known power outage - working to restore power",
    "Area": "Beecroft",
    "Cause": "Under investigation",
    "Customers": "18",
    "EstRestTime": "2024-01-07T21:00:00",
    "StartDateTime": "2024-01-07T16:10:00",
    "WebId": 99570,
    "Status": 1
  },
  {
    "StatusHeading": "Known power outage - working to restore power",
    "Area": "Summer Hill",
    "Cause": "Under investigation",
    "Customers": "less than 10",
    "EstRestTime": "2024-01-07T21:00:00",
    "StartDateTime": "2024-01-07T15:50:00",
    "WebId": 99571,
    "Status": 1
  }
]
